lfss/__init__.py
lfss/api/__init__.py
lfss/api/bundle.py
lfss/api/connector.py
lfss/cli/__init__.py
lfss/cli/balance.py
lfss/cli/cli.py
lfss/cli/cli_lib.py
lfss/cli/log.py
lfss/cli/serve.py
lfss/cli/user.py
lfss/cli/vacuum.py
lfss/eng/__init__.py
lfss/eng/bounded_pool.py
lfss/eng/config.py
lfss/eng/connection_pool.py
lfss/eng/database.py
lfss/eng/database_conn.py
lfss/eng/datatype.py
lfss/eng/dir_config.py
lfss/eng/error.py
lfss/eng/log.py
lfss/eng/permission.py
lfss/eng/thumb.py
lfss/eng/typing_helpers.py
lfss/eng/userman.py
lfss/eng/utils.py
lfss/sql/init.sql
lfss/sql/pragma.sql
lfss/svc/app.py
lfss/svc/app_base.py
lfss/svc/app_dav.py
lfss/svc/app_native.py
lfss/svc/app_native_user.py
lfss/svc/common_impl.py
lfss/svc/request_log.py
lfss/svc/static/.gitkeep
lfss/svc/static/docs/404.html
lfss/svc/static/docs/Development.html
lfss/svc/static/docs/_known-issues.html
lfss/svc/static/docs/assets/Development.md.bp4RPMej.js
lfss/svc/static/docs/assets/Development.md.bp4RPMej.lean.js
lfss/svc/static/docs/assets/app.DO6qBcjA.js
lfss/svc/static/docs/assets/arch.DOFLzA6U.svg
lfss/svc/static/docs/assets/changelogs.md.CiLFbrUo.js
lfss/svc/static/docs/assets/changelogs.md.CiLFbrUo.lean.js
lfss/svc/static/docs/assets/chunks/framework.CkHvLvtj.js
lfss/svc/static/docs/assets/chunks/theme.D1W8Jws6.js
lfss/svc/static/docs/assets/client-intro.md.BMRgAuIn.js
lfss/svc/static/docs/assets/client-intro.md.BMRgAuIn.lean.js
lfss/svc/static/docs/assets/commands.md.BhLvxjOX.js
lfss/svc/static/docs/assets/commands.md.BhLvxjOX.lean.js
lfss/svc/static/docs/assets/environment-variables.md.9WpFz9y4.js
lfss/svc/static/docs/assets/environment-variables.md.9WpFz9y4.lean.js
lfss/svc/static/docs/assets/index.md.BTQ0N3NC.js
lfss/svc/static/docs/assets/index.md.BTQ0N3NC.lean.js
lfss/svc/static/docs/assets/inter-italic-cyrillic-ext.r48I6akx.woff2
lfss/svc/static/docs/assets/inter-italic-cyrillic.By2_1cv3.woff2
lfss/svc/static/docs/assets/inter-italic-greek-ext.1u6EdAuj.woff2
lfss-0.16.0.dist-info/METADATA
lfss-0.16.0.dist-info/WHEEL
lfss-0.16.0.dist-info/entry_points.txt
lfss-0.16.0.dist-info/RECORD
