Metadata-Version: 2.3
Name: lfss
Version: 0.16.0
Summary: Lite file storage service
Author: Li, Mengxun
Author-email: mengxunli@whu.edu.cn
Requires-Python: >=3.10
Classifier: Programming Language :: Python :: 3
Classifier: Programming Language :: Python :: 3.10
Classifier: Programming Language :: Python :: 3.11
Classifier: Programming Language :: Python :: 3.12
Classifier: Programming Language :: Python :: 3.13
Provides-Extra: all
Requires-Dist: aiofiles (==25.*) ; extra == "all"
Requires-Dist: aiosqlite (==0.*) ; extra == "all"
Requires-Dist: fastapi[standard] (==0.*) ; extra == "all"
Requires-Dist: mimesniff (==1.*) ; extra == "all"
Requires-Dist: pillow ; extra == "all"
Requires-Dist: requests (==2.*)
Requires-Dist: rich ; extra == "all"
Requires-Dist: stream-zip (==0.*) ; extra == "all"
Project-URL: Homepage, https://github.com/MenxLi/lfss
Project-URL: Repository, https://github.com/MenxLi/lfss
